<annotation>
	<folder>Give Way Signs</folder>
	<filename>giveway55.jpg</filename>
	<path>C:\Users\linds\Documents\Lindsay Uni\ELEC3850\windows_v1.8.0\windows_v1.8.0\Give Way Signs\giveway55.jpg</path>
	<source>
		<database>Unknown</database>
	</source>
	<size>
		<width>190</width>
		<height>265</height>
		<depth>3</depth>
	</size>
	<segmented>0</segmented>
	<object>
		<name>giveway</name>
		<pose>Unspecified</pose>
		<truncated>0</truncated>
		<difficult>0</difficult>
		<bndbox>
			<xmin>29</xmin>
			<ymin>14</ymin>
			<xmax>172</xmax>
			<ymax>164</ymax>
		</bndbox>
	</object>
	<object>
		<name>giveway</name>
		<pose>Unspecified</pose>
		<truncated>0</truncated>
		<difficult>0</difficult>
		<bndbox>
			<xmin>28</xmin>
			<ymin>21</ymin>
			<xmax>98</xmax>
			<ymax>154</ymax>
		</bndbox>
	</object>
	<object>
		<name>giveway</name>
		<pose>Unspecified</pose>
		<truncated>0</truncated>
		<difficult>0</difficult>
		<bndbox>
			<xmin>104</xmin>
			<ymin>21</ymin>
			<xmax>157</xmax>
			<ymax>132</ymax>
		</bndbox>
	</object>
	<object>
		<name>giveway</name>
		<pose>Unspecified</pose>
		<truncated>0</truncated>
		<difficult>0</difficult>
		<bndbox>
			<xmin>45</xmin>
			<ymin>58</ymin>
			<xmax>147</xmax>
			<ymax>138</ymax>
		</bndbox>
	</object>
	<object>
		<name>giveway</name>
		<pose>Unspecified</pose>
		<truncated>0</truncated>
		<difficult>0</difficult>
		<bndbox>
			<xmin>32</xmin>
			<ymin>24</ymin>
			<xmax>166</xmax>
			<ymax>66</ymax>
		</bndbox>
	</object>
</annotation>
